unbirthday/__init__.py
unbirthday/unbirthday.py
unbirthday-1.0.4.dist-info/METADATA
unbirthday-1.0.4.dist-info/WHEEL
unbirthday-1.0.4.dist-info/top_level.txt
unbirthday-1.0.4.dist-info/RECORD
