Metadata-Version: 2.1
Name: unbirthday
Version: 1.0.4
Summary: Unbirthday is a Python module that provides functions to calculate and manage "unbirthdays," which are days celebrated as not being a person's birthday.
